pyreminder/__init__.py
pyreminder/constants.py
pyreminder/create_remind.py
pyreminder/pr.py
pyreminder/reminders_io.py
pyreminder/utils.py
pyreminder-0.1.2.data/scripts/pyreminder
pyreminder-0.1.2.dist-info/LICENSE
pyreminder-0.1.2.dist-info/METADATA
pyreminder-0.1.2.dist-info/WHEEL
pyreminder-0.1.2.dist-info/top_level.txt
pyreminder-0.1.2.dist-info/RECORD
