Metadata-Version: 2.1
Name: pyreminder
Version: 0.1.2
Summary: Python library to create iCloud Reminders through CLI
Home-page: http://github.com/ohitssway/pyreminder
Author: Saimun Shahee
Author-email: saimun.shahee@gmail.com
License: MIT
Platform: UNKNOWN
